embyapi/__init__.py
embyapi/api_client.py
embyapi/configuration.py
embyapi/rest.py
embyapi/api/__init__.py
embyapi/api/activity_log_service_api.py
embyapi/api/artists_service_api.py
embyapi/api/audio_service_api.py
embyapi/api/bif_service_api.py
embyapi/api/branding_service_api.py
embyapi/api/channel_service_api.py
embyapi/api/collection_service_api.py
embyapi/api/configuration_service_api.py
embyapi/api/connect_service_api.py
embyapi/api/dashboard_service_api.py
embyapi/api/device_service_api.py
embyapi/api/display_preferences_service_api.py
embyapi/api/dlna_server_service_api.py
embyapi/api/dlna_service_api.py
embyapi/api/dynamic_hls_service_api.py
embyapi/api/encoding_info_service_api.py
embyapi/api/environment_service_api.py
embyapi/api/ffmpeg_options_service_api.py
embyapi/api/filter_service_api.py
embyapi/api/game_genres_service_api.py
embyapi/api/games_service_api.py
embyapi/api/genres_service_api.py
embyapi/api/hls_segment_service_api.py
embyapi/api/image_by_name_service_api.py
embyapi/api/image_service_api.py
embyapi/api/instant_mix_service_api.py
embyapi/api/io_service_api.py
embyapi/api/item_lookup_service_api.py
embyapi/api/item_refresh_service_api.py
embyapi/api/item_update_service_api.py
embyapi/api/items_service_api.py
embyapi/api/library_service_api.py
embyapi/api/library_structure_service_api.py
embyapi/api/live_tv_service_api.py
embyapi/api/localization_service_api.py
embyapi/api/media_info_service_api.py
embyapi/api/movies_service_api.py
embyapi/api/music_genres_service_api.py
embyapi/api/news_service_api.py
embyapi/api/notifications_api_api.py
embyapi/api/notifications_service_api.py
embyapi/api/official_rating_service_api.py
embyapi/api/open_api_service_api.py
embyapi/api/package_service_api.py
embyapi/api/persons_service_api.py
embyapi/api/playlist_info_service_api.py
embyapi/api/playlist_log_service_api.py
embyapi/api/playlist_service_api.py
embyapi/api/playstate_service_api.py
embyapi/api/plugin_service_api.py
EmbyServerAPI-3.2.2.dist-info/METADATA
EmbyServerAPI-3.2.2.dist-info/WHEEL
EmbyServerAPI-3.2.2.dist-info/top_level.txt
EmbyServerAPI-3.2.2.dist-info/RECORD
