Metadata-Version: 2.1
Name: EmbyServerAPI
Version: 3.2.2
Summary: Emby REST API
Home-page: UNKNOWN
Author-email: 
License: UNKNOWN
Keywords: Swagger,Emby REST API
Platform: UNKNOWN
Requires-Dist: certifi
Requires-Dist: python-dateutil
Requires-Dist: six (>=1.10)
Requires-Dist: urllib3 (>=1.15)
